LOGS/LOGS.py
LOGS/LOGSConnection.py
LOGS/LOGSOptions.py
LOGS/ServerMetaData.py
LOGS/__init__.py
LOGS/Auxiliary/CheckClassName.py
LOGS/Auxiliary/Constants.py
LOGS/Auxiliary/CustomEntityClassGenerator.py
LOGS/Auxiliary/CustomFieldClassGenerator.py
LOGS/Auxiliary/CustomFieldValueTypeChecker.py
LOGS/Auxiliary/CustomSectionClassGenerator.py
LOGS/Auxiliary/CustomTypeClassGenerator.py
LOGS/Auxiliary/DateTimeConverter.py
LOGS/Auxiliary/Decorators.py
LOGS/Auxiliary/Exceptions.py
LOGS/Auxiliary/LOGSErrorResponse.py
LOGS/Auxiliary/MinimalModelGenerator.py
LOGS/Auxiliary/ParameterHelper.py
LOGS/Auxiliary/ReplaceMessage.py
LOGS/Auxiliary/Tools.py
LOGS/Auxiliary/__init__.py
LOGS/Converter/Conversion.py
LOGS/Converter/Converter.py
LOGS/Converter/ConverterParameter.py
LOGS/Converter/DateTimeRange.py
LOGS/Converter/ExportParameters.py
LOGS/Converter/__init__.py
LOGS/Entities/Attachment.py
LOGS/Entities/AttachmentMinimal.py
LOGS/Entities/AttachmentRequestParameter.py
LOGS/Entities/Attachments.py
LOGS/Entities/AutoloadFileInfo.py
LOGS/Entities/AutoloadStatusError.py
LOGS/Entities/AxisNaming.py
LOGS/Entities/AxisZoom.py
LOGS/Entities/Bridge.py
LOGS/Entities/BridgeClientInfo.py
LOGS/Entities/BridgeMinimal.py
LOGS/Entities/BridgeRequestParameter.py
LOGS/Entities/BridgeType.py
LOGS/Entities/Bridges.py
LOGS/Entities/CustomField.py
LOGS/Entities/CustomFieldMinimal.py
LOGS/Entities/CustomFieldModels.py
LOGS/Entities/CustomFieldRequestParameter.py
LOGS/Entities/CustomFieldSearchQuery.py
LOGS/Entities/CustomFields.py
LOGS/Entities/CustomType.py
LOGS/Entities/CustomTypeEntityTypeMapper.py
LOGS/Entities/CustomTypeMinimal.py
LOGS/Entities/CustomTypeRequestParameter.py
LOGS/Entities/CustomTypeSection.py
LOGS/Entities/CustomTypes.py
LOGS/Entities/DataFormat.py
LOGS/Entities/DataFormatInstrument.py
LOGS/Entities/DataFormatInstrumentMinimal.py
LOGS/Entities/DataFormatInstrumentRequestParameter.py
LOGS/Entities/DataFormatInstruments.py
LOGS/Entities/DataFormatMinimal.py
logs_py-4.0.17.dist-info/METADATA
logs_py-4.0.17.dist-info/WHEEL
logs_py-4.0.17.dist-info/top_level.txt
logs_py-4.0.17.dist-info/RECORD
