Metadata-Version: 2.4
Name: logs-py
Version: 4.0.17
Summary: A python interface for the LOGS public API
Home-page: https://docs.logs-python.com
Author: Sina Kazemi
Author-email: support@logs-repository.com
License: MIT
Classifier: Programming Language :: Python :: 3
Classifier: License :: OSI Approved :: MIT License
Classifier: Operating System :: OS Independent
Classifier: Development Status :: 4 - Beta
Classifier: Intended Audience :: Science/Research
Requires-Python: >=3.8
Requires-Dist: numpy
Requires-Dist: requests
Requires-Dist: regex>=2019.12.9
Requires-Dist: Pillow
Requires-Dist: deprecation
Requires-Dist: pytz
Requires-Dist: tzlocal; platform_system == "Windows"
Requires-Dist: typing_extensions
Dynamic: author
Dynamic: author-email
Dynamic: classifier
Dynamic: description
Dynamic: description-content-type
Dynamic: home-page
Dynamic: license
Dynamic: requires-dist
Dynamic: requires-python
Dynamic: summary
